eudplib-0.80.6.dist-info/METADATA
eudplib-0.80.6.dist-info/WHEEL
eudplib-0.80.6.dist-info/licenses/LICENSE
eudplib/LICENSE
eudplib/__init__.py
eudplib/bindings/__init__.py
eudplib/bindings/_rust.pyd
eudplib/bindings/_rust/__init__.pyi
eudplib/bindings/_rust/allocator.pyi
eudplib/bindings/_rust/epscript.pyi
eudplib/bindings/_rust/eudobj.pyi
eudplib/bindings/_rust/mpqapi.pyi
eudplib/collections/__init__.py
eudplib/collections/eudarray.py
eudplib/collections/eudqueue.py
eudplib/collections/eudstack.py
eudplib/collections/objpool.py
eudplib/collections/playerv.py
eudplib/collections/unitgroup.py
eudplib/core/__init__.py
eudplib/core/allocator/__init__.py
eudplib/core/allocator/constexpr.py
eudplib/core/allocator/payload.py
eudplib/core/allocator/pbuffer.py
eudplib/core/allocator/rlocint.py
eudplib/core/calcf/__init__.py
eudplib/core/calcf/_eudvsupport.py
eudplib/core/calcf/bitwise.py
eudplib/core/calcf/muldiv.py
eudplib/core/curpl.py
eudplib/core/eudfunc/__init__.py
eudplib/core/eudfunc/eudf.py
eudplib/core/eudfunc/eudfmethod.py
eudplib/core/eudfunc/eudfptr.py
eudplib/core/eudfunc/eudfuncn.py
eudplib/core/eudfunc/eudtypedfuncn.py
eudplib/core/eudfunc/trace/__init__.py
eudplib/core/eudfunc/trace/tracecrypt.py
eudplib/core/eudfunc/trace/tracetool.py
eudplib/core/eudobj/__init__.py
eudplib/core/eudobj/bytedump.py
eudplib/core/eudobj/eudobj.py
eudplib/core/eudstruct/__init__.py
eudplib/core/eudstruct/eudstruct.py
eudplib/core/eudstruct/selftype.py
eudplib/core/eudstruct/structarr.py
eudplib/core/eudstruct/vararray.py
eudplib/core/inlinens.py
eudplib/core/inplacecw.py
eudplib/core/mapdata/__init__.py
eudplib/core/mapdata/chktok.py
eudplib/core/mapdata/fixmapdata.py
eudplib/core/mapdata/mapdata.py
eudplib/core/mapdata/playerinfo.py
eudplib/core/mapdata/proptable.py
eudplib/core/mapdata/stringmap.py
eudplib/core/mapdata/tblformat.py
eudplib/core/mapdata/unitprp.py
eudplib/core/rawtrigger/__init__.py
eudplib/core/rawtrigger/action.py
eudplib/core/rawtrigger/condition.py
eudplib/core/rawtrigger/constenc.py
eudplib/core/rawtrigger/consttype.py
eudplib/core/rawtrigger/rawtriggerdef.py
eudplib-0.80.6.dist-info/RECORD
