Metadata-Version: 2.4
Name: eudplib
Version: 0.80.6
Classifier: Development Status :: 5 - Production/Stable
Classifier: Intended Audience :: Developers
Classifier: License :: OSI Approved :: MIT License
Classifier: Natural Language :: English
Classifier: Operating System :: POSIX :: Linux
Classifier: Operating System :: Microsoft :: Windows
Classifier: Programming Language :: Python
Classifier: Programming Language :: Python :: 3
Classifier: Programming Language :: Python :: 3 :: Only
Classifier: Programming Language :: Python :: 3.10
Classifier: Programming Language :: Python :: 3.11
Classifier: Programming Language :: Python :: 3.12
Classifier: Programming Language :: Python :: 3.13
Classifier: Programming Language :: Python :: Implementation :: CPython
Classifier: Topic :: Games/Entertainment :: Real Time Strategy
Requires-Dist: typing-extensions
License-File: LICENSE
Summary: eudplib is a package which provides scripting for StarCraft Use Map Setting(UMS) to UMS map and tool developers.
Keywords: StarCraft,EUD,Trigger
Author-email: Trgk <whyask37@naver.com>, Armoha <kein0011@naver.com>
Maintainer-email: Armoha <kein0011@naver.com>
License: MIT
Requires-Python: >=3.10, <3.14
Project-URL: homepage, https://github.com/armoha/eudplib/
Project-URL: documentation, https://github.com/armoha/euddraft/wiki
Project-URL: source, https://github.com/armoha/eudplib/
Project-URL: issues, https://github.com/armoha/euddraft/issues
Project-URL: changelog, https://github.com/armoha/euddraft/blob/master/CHANGELOG.md
